ytgrep.py
test/__init__.py
test/functional/__init__.py
test/functional/test_real_video.py
test/unit/__init__.py
test/unit/download/__init__.py
test/unit/download/test_get_captions.py
test/unit/download/test_get_result.py
test/unit/storage/__init__.py
test/unit/storage/test_get_file_path.py
test/unit/storage/test_remove_file.py
ytcc/__init__.py
ytcc/download.py
ytcc/storage.py
ytgrep-0.5.0.dist-info/LICENSE
ytgrep-0.5.0.dist-info/METADATA
ytgrep-0.5.0.dist-info/WHEEL
ytgrep-0.5.0.dist-info/entry_points.txt
ytgrep-0.5.0.dist-info/top_level.txt
ytgrep-0.5.0.dist-info/RECORD
