Metadata-Version: 2.1
Name: ytgrep
Version: 0.5.0
Summary: CLI tool to search youtube captions
Home-page: UNKNOWN
Author: Alex Kohler
Author-email: alexjohnkohler@gmail.com
License: UNKNOWN
Platform: UNKNOWN
Classifier: Programming Language :: Python :: 3.7
Requires-Dist: colorama (>=0.4.1)
Requires-Dist: pycaption (>=1.0.1)
Requires-Dist: youtube-dl (>=2019.4.24)
